QQt/__about__.py
QQt/__config__.py
QQt/__init__.py
QQt/_emmiter.py
QQt/_signal.py
QQt/vtkmodules/qt/QVTKRenderWindowInteractor.py
QQt/vtkmodules/qt/__init__.py
QQt-1.2.1.dist-info/LICENSE
QQt-1.2.1.dist-info/METADATA
QQt-1.2.1.dist-info/WHEEL
QQt-1.2.1.dist-info/top_level.txt
QQt-1.2.1.dist-info/zip-safe
QQt-1.2.1.dist-info/RECORD
